plex2mix/__init__.py
plex2mix/downloader.py
plex2mix/exporter.py
plex2mix/init.py
plex2mix/main.py
plex2mix-1.0.1.dist-info/licenses/LICENSE
plex2mix-1.0.1.dist-info/METADATA
plex2mix-1.0.1.dist-info/WHEEL
plex2mix-1.0.1.dist-info/entry_points.txt
plex2mix-1.0.1.dist-info/top_level.txt
plex2mix-1.0.1.dist-info/RECORD
