Metadata-Version: 2.4
Name: plex2mix
Version: 1.0.1
Summary: 🎵 Plex2Mix - A powerful Plex music downloader designed for DJs and music enthusiasts. Download playlists locally with track deduplication, export to multiple formats (M3U8, JSON, iTunes XML), and manage your music library with an intuitive interactive CLI. Perfect for importing into Rekordbox, Traktor, Mixxx, or iTunes. 
Home-page: https://github.com/anatosun/plex2mix
Author: Anatosun
Author-email: anatosun <z4jyol8l@duck.com>
License: GPL-3.0-or-later
Project-URL: Homepage, https://github.com/anatosun/plex2mix
Project-URL: Repository, https://github.com/anatosun/plex2mix
Project-URL: Documentation, https://github.com/anatosun/plex2mix#readme
Project-URL: Bug Reports, https://github.com/anatosun/plex2mix/issues
Keywords: plex,music,dj,downloader,playlist,m3u8,itunes
Classifier: Development Status :: 4 - Beta
Classifier: Intended Audience :: End Users/Desktop
Classifier: License :: OSI Approved :: MIT License
Classifier: Operating System :: OS Independent
Classifier: Programming Language :: Python :: 3
Classifier: Programming Language :: Python :: 3.8
Classifier: Programming Language :: Python :: 3.9
Classifier: Programming Language :: Python :: 3.10
Classifier: Programming Language :: Python :: 3.11
Classifier: Programming Language :: Python :: 3.12
Classifier: Topic :: Multimedia :: Sound/Audio
Classifier: Topic :: System :: Archiving
Requires-Python: >=3.8
License-File: LICENSE
Requires-Dist: click>=8.0
Requires-Dist: plexapi>=4.9
Requires-Dist: pyyaml>=6.0
Provides-Extra: dev
Requires-Dist: pytest>=7.0; extra == "dev"
Requires-Dist: pytest-cov>=4.0; extra == "dev"
Requires-Dist: black>=22.0; extra == "dev"
Requires-Dist: flake8>=5.0; extra == "dev"
Requires-Dist: mypy>=1.0; extra == "dev"
Requires-Dist: build>=0.8; extra == "dev"
Requires-Dist: twine>=4.0; extra == "dev"
Dynamic: author
Dynamic: home-page
Dynamic: license-file
Dynamic: requires-python
